src/fpu/fp_gt.v
// Using IEEE-754 Single Precision Float

/*
    fp_gt: listens to two 32 bit inputs which should represent 2 floating point
    precision numbers. It sets out if f1 > f2, else it zeros out.

    This is the main driver for looking at the technical indicators. Under IEEE-754
    we can compare the binary representation the same as we would for normal integers.
*/
module fp_gt (output out, input [31:0] f1, input [31:0] f2);

    reg out = 1'b0;

    always @ (*)
    begin 
        if (f1[31] == 1 && f2[31] == 1)
        begin 
            if (f1[30:0] > f2[30:0])
            begin
                out = 1'b0;
            end
            else
            begin
                out = 1'b1;
            end
        end
        else if (f1[31] == 0 && f2[31] == 0)
        begin
            if (f1[30:0] > f2[30:0])
            begin
                out = 1'b1;
            end
            else
            begin
                out = 1'b0;
            end
        end
        else
        begin
            if (f1[31] == 1)
            begin
                out = 1'b0;
            end
            else
            begin
                out = 1'b1;
            end
        end
    end
endmodule

src/fpu/tests/fp_gt_tb.v
`timescale 1ns / 1ps
`include "../fp_gt.v"

module dev_tb();
    reg [31:0] F1;
    reg [31:0] F2;

    wire RESULT;

    fp_gt uut (.out(RESULT), .f1(F1), .f2(F2));

    initial begin
        $monitor("F1=%d, F2=%d, RESULT=%b", F1[30:0], F2[30:0], RESULT);
        $dumpfile("fp_gt.vcd");
        $dumpvars(0, dev_tb);
        
        // Expect: 1
        F1 = 32'b01000001010000000000000000000000; // 12 
        F2 = 32'b11000001010000000000000000000000; // -12
        #100000;

        // Expect: 0
        F1 = 32'b11000001010000000000000000000000; // -12
        F2 = 32'b01000001010000000000000000000000; // 12
        #100000;

        // Expect: 0
        F1 = 32'b00000000000000000000000000000000; // 0
        F2 = 32'b01000001010101100110011001100110; // 13.4
        #100000;

        // Expect: 1
        F1 = 32'b01000001010101100110011001100110; // 13.4
        F2 = 32'b00000000000000000000000000000000; // 0
        #100000;

        // Expect: 1
        F1 = 32'b00000000000000000000000000000000; // 0
        F2 = 32'b11000001001000111010111000010100; // -10.23
        #100000;

        // Expect: 0
        F1 = 32'b11000001001000111010111000010100; // -10.23
        F2 = 32'b00000000000000000000000000000000; // 0
        #100000;

        // Expect: 1
        F1 = 32'b01000001110001000111101011100001; // 24.56
        F2 = 32'b01000001001000111010111000010100; // 10.23
        #100000;

        // Expect: 0
        F1 = 32'b01000001001000111010111000010100; // 10.23
        F2 = 32'b01000001110001000111101011100001; // 24.56
        #100000;

        // Expect: 0
        F1 = 32'b11000010000010100011110101110001; // -34.56
        F2 = 32'b11000001011001010111000010100100; // -14.34
        #100000;

        // Expect: 1
        F1 = 32'b11000001011001010111000010100100; // -14.34 
        F2 = 32'b11000010000010100011110101110001; // -34.56
        #100000;
        $finish;
    end

endmodule

src/fpu/tests/vcd/fp_gt.vcd
$date
	Mon Jun 29 20:48:48 2020
$end
$version
	Icarus Verilog
$end
$timescale
	1ps
$end
$scope module dev_tb $end
$var wire 1 ! RESULT $end
$var reg 32 " F1 [31:0] $end
$var reg 32 # F2 [31:0] $end
$scope module uut $end
$var wire 32 $ f1 [31:0] $end
$var wire 32 % f2 [31:0] $end
$var reg 1 ! out $end
$upscope $end
$upscope $end
$enddefinitions $end
#0
$dumpvars
b11000001010000000000000000000000 %
b1000001010000000000000000000000 $
b11000001010000000000000000000000 #
b1000001010000000000000000000000 "
1!
$end
#100000000
0!
b1000001010000000000000000000000 #
b1000001010000000000000000000000 %
b11000001010000000000000000000000 "
b11000001010000000000000000000000 $
#200000000
b1000001010101100110011001100110 #
b1000001010101100110011001100110 %
b0 "
b0 $
#300000000
1!
b0 #
b0 %
b1000001010101100110011001100110 "
b1000001010101100110011001100110 $
#400000000
b11000001001000111010111000010100 #
b11000001001000111010111000010100 %
b0 "
b0 $
#500000000
0!
b0 #
b0 %
b11000001001000111010111000010100 "
b11000001001000111010111000010100 $
#600000000
1!
b1000001001000111010111000010100 #
b1000001001000111010111000010100 %
b1000001110001000111101011100001 "
b1000001110001000111101011100001 $
#700000000
0!
b1000001110001000111101011100001 #
b1000001110001000111101011100001 %
b1000001001000111010111000010100 "
b1000001001000111010111000010100 $
#800000000
b11000001011001010111000010100100 #
b11000001011001010111000010100100 %
b11000010000010100011110101110001 "
b11000010000010100011110101110001 $
#900000000
1!
b11000010000010100011110101110001 #
b11000010000010100011110101110001 %
b11000001011001010111000010100100 "
b11000001011001010111000010100100 $
